{
  "version": 1,
  "tree_id": "20260430-DAMIMAS-166",
  "tree_name": "DAMIMAS_A21B_0708",
  "split": "train",
  "metadata": {
    "date": "2026-04-30",
    "varietas": "DAMIMAS",
    "number": 166,
    "generated_at": "2026-04-30T01:57:30.273Z"
  },
  "images": {
    "sisi_1": {
      "filename": "DAMIMAS_A21B_0708_1.jpg",
      "label_file": "DAMIMAS_A21B_0708_1.txt",
      "side_index": 0,
      "side_label": "Sisi 1",
      "width": 960,
      "height": 1280,
      "bbox_count": 8,
      "annotations": [
        {
          "box_index": 0,
          "class_id": 0,
          "class_name": "B1",
          "bbox_yolo": [
            0.21233,
            0.42753,
            0.195312,
            0.151027
          ],
          "bbox_pixel": [
            110,
            451,
            298,
            644
          ]
        },
        {
          "box_index": 1,
          "class_id": 2,
          "class_name": "B3",
          "bbox_yolo": [
            0.372063,
            0.349178,
            0.23922,
            0.19077
          ],
          "bbox_pixel": [
            242,
            325,
            472,
            569
          ]
        },
        {
          "box_index": 2,
          "class_id": 2,
          "class_name": "B3",
          "bbox_yolo": [
            0.218008,
            0.263161,
            0.090086,
            0.091411
          ],
          "bbox_pixel": [
            166,
            278,
            253,
            395
          ]
        },
        {
          "box_index": 3,
          "class_id": 3,
          "class_name": "B4",
          "bbox_yolo": [
            0.34216,
            0.18708,
            0.132479,
            0.124341
          ],
          "bbox_pixel": [
            265,
            160,
            392,
            319
          ]
        },
        {
          "box_index": 4,
          "class_id": 2,
          "class_name": "B3",
          "bbox_yolo": [
            0.571539,
            0.233637,
            0.238463,
            0.147052
          ],
          "bbox_pixel": [
            434,
            205,
            663,
            393
          ]
        },
        {
          "box_index": 5,
          "class_id": 2,
          "class_name": "B3",
          "bbox_yolo": [
            0.856937,
            0.273948,
            0.202126,
            0.120935
          ],
          "bbox_pixel": [
            726,
            273,
            920,
            428
          ]
        },
        {
          "box_index": 6,
          "class_id": 3,
          "class_name": "B4",
          "bbox_yolo": [
            0.794104,
            0.179983,
            0.071917,
            0.059048
          ],
          "bbox_pixel": [
            728,
            193,
            797,
            268
          ]
        },
        {
          "box_index": 7,
          "class_id": 1,
          "class_name": "B2",
          "bbox_yolo": [
            0.690392,
            0.398574,
            0.241491,
            0.154433
          ],
          "bbox_pixel": [
            547,
            411,
            779,
            609
          ]
        }
      ]
    },
    "sisi_2": {
      "filename": "DAMIMAS_A21B_0708_2.jpg",
      "label_file": "DAMIMAS_A21B_0708_2.txt",
      "side_index": 1,
      "side_label": "Sisi 2",
      "width": 960,
      "height": 1280,
      "bbox_count": 7,
      "annotations": [
        {
          "box_index": 0,
          "class_id": 0,
          "class_name": "B1",
          "bbox_yolo": [
            0.664621,
            0.452916,
            0.355283,
            0.19043
          ],
          "bbox_pixel": [
            468,
            458,
            809,
            702
          ]
        },
        {
          "box_index": 1,
          "class_id": 2,
          "class_name": "B3",
          "bbox_yolo": [
            0.529762,
            0.287249,
            0.323661,
            0.267857
          ],
          "bbox_pixel": [
            353,
            196,
            664,
            539
          ]
        },
        {
          "box_index": 2,
          "class_id": 3,
          "class_name": "B4",
          "bbox_yolo": [
            0.229818,
            0.182617,
            0.233445,
            0.184152
          ],
          "bbox_pixel": [
            109,
            116,
            333,
            352
          ]
        },
        {
          "box_index": 3,
          "class_id": 2,
          "class_name": "B3",
          "bbox_yolo": [
            0.245629,
            0.365723,
            0.235305,
            0.20159
          ],
          "bbox_pixel": [
            123,
            339,
            349,
            597
          ]
        },
        {
          "box_index": 4,
          "class_id": 2,
          "class_name": "B3",
          "bbox_yolo": [
            0.828311,
            0.30678,
            0.193452,
            0.160435
          ],
          "bbox_pixel": [
            702,
            290,
            888,
            495
          ]
        },
        {
          "box_index": 5,
          "class_id": 2,
          "class_name": "B3",
          "bbox_yolo": [
            0.836682,
            0.181222,
            0.126488,
            0.066964
          ],
          "bbox_pixel": [
            743,
            189,
            864,
            275
          ]
        },
        {
          "box_index": 6,
          "class_id": 3,
          "class_name": "B4",
          "bbox_yolo": [
            0.71461,
            0.104538,
            0.091514,
            0.073703
          ],
          "bbox_pixel": [
            642,
            87,
            730,
            181
          ]
        }
      ]
    },
    "sisi_3": {
      "filename": "DAMIMAS_A21B_0708_3.jpg",
      "label_file": "DAMIMAS_A21B_0708_3.txt",
      "side_index": 2,
      "side_label": "Sisi 3",
      "width": 960,
      "height": 1280,
      "bbox_count": 7,
      "annotations": [
        {
          "box_index": 0,
          "class_id": 1,
          "class_name": "B2",
          "bbox_yolo": [
            0.159778,
            0.439752,
            0.189012,
            0.145697
          ],
          "bbox_pixel": [
            63,
            470,
            244,
            656
          ]
        },
        {
          "box_index": 1,
          "class_id": 3,
          "class_name": "B4",
          "bbox_yolo": [
            0.42619,
            0.180267,
            0.173359,
            0.102766
          ],
          "bbox_pixel": [
            326,
            165,
            492,
            297
          ]
        },
        {
          "box_index": 2,
          "class_id": 2,
          "class_name": "B3",
          "bbox_yolo": [
            0.226714,
            0.287859,
            0.1832,
            0.170331
          ],
          "bbox_pixel": [
            130,
            259,
            306,
            477
          ]
        },
        {
          "box_index": 3,
          "class_id": 2,
          "class_name": "B3",
          "bbox_yolo": [
            0.485617,
            0.359398,
            0.35126,
            0.203261
          ],
          "bbox_pixel": [
            298,
            330,
            635,
            590
          ]
        },
        {
          "box_index": 4,
          "class_id": 0,
          "class_name": "B1",
          "bbox_yolo": [
            0.819465,
            0.434911,
            0.233164,
            0.198719
          ],
          "bbox_pixel": [
            675,
            430,
            899,
            684
          ]
        },
        {
          "box_index": 5,
          "class_id": 3,
          "class_name": "B4",
          "bbox_yolo": [
            0.692284,
            0.224269,
            0.174116,
            0.158975
          ],
          "bbox_pixel": [
            581,
            185,
            748,
            389
          ]
        },
        {
          "box_index": 6,
          "class_id": 2,
          "class_name": "B3",
          "bbox_yolo": [
            0.843689,
            0.281329,
            0.145349,
            0.117528
          ],
          "bbox_pixel": [
            740,
            285,
            880,
            435
          ]
        }
      ]
    },
    "sisi_4": {
      "filename": "DAMIMAS_A21B_0708_4.jpg",
      "label_file": "DAMIMAS_A21B_0708_4.txt",
      "side_index": 3,
      "side_label": "Sisi 4",
      "width": 960,
      "height": 1280,
      "bbox_count": 6,
      "annotations": [
        {
          "box_index": 0,
          "class_id": 1,
          "class_name": "B2",
          "bbox_yolo": [
            0.80977,
            0.48543,
            0.302419,
            0.219727
          ],
          "bbox_pixel": [
            632,
            481,
            923,
            762
          ]
        },
        {
          "box_index": 1,
          "class_id": 2,
          "class_name": "B3",
          "bbox_yolo": [
            0.841797,
            0.32162,
            0.211064,
            0.134671
          ],
          "bbox_pixel": [
            707,
            325,
            909,
            498
          ]
        },
        {
          "box_index": 2,
          "class_id": 2,
          "class_name": "B3",
          "bbox_yolo": [
            0.665911,
            0.268854,
            0.243616,
            0.2024
          ],
          "bbox_pixel": [
            522,
            215,
            756,
            474
          ]
        },
        {
          "box_index": 3,
          "class_id": 3,
          "class_name": "B4",
          "bbox_yolo": [
            0.373992,
            0.247196,
            0.207913,
            0.177986
          ],
          "bbox_pixel": [
            259,
            202,
            459,
            430
          ]
        },
        {
          "box_index": 4,
          "class_id": 2,
          "class_name": "B3",
          "bbox_yolo": [
            0.18813,
            0.38108,
            0.256216,
            0.269342
          ],
          "bbox_pixel": [
            58,
            315,
            304,
            660
          ]
        },
        {
          "box_index": 5,
          "class_id": 2,
          "class_name": "B3",
          "bbox_yolo": [
            0.496325,
            0.420457,
            0.227865,
            0.193737
          ],
          "bbox_pixel": [
            367,
            414,
            586,
            662
          ]
        }
      ]
    }
  },
  "bunches": [
    {
      "bunch_id": 1,
      "class": "B1",
      "class_mismatch": false,
      "appearance_count": 3,
      "appearances": [
        {
          "side": "sisi_1",
          "side_index": 0,
          "box_index": 0,
          "class_name": "B1",
          "bbox_pixel": [
            110,
            451,
            298,
            644
          ]
        },
        {
          "side": "sisi_2",
          "side_index": 1,
          "box_index": 0,
          "class_name": "B1",
          "bbox_pixel": [
            468,
            458,
            809,
            702
          ]
        },
        {
          "side": "sisi_3",
          "side_index": 2,
          "box_index": 4,
          "class_name": "B1",
          "bbox_pixel": [
            675,
            430,
            899,
            684
          ]
        }
      ]
    },
    {
      "bunch_id": 2,
      "class": "B3",
      "class_mismatch": false,
      "appearance_count": 2,
      "appearances": [
        {
          "side": "sisi_1",
          "side_index": 0,
          "box_index": 1,
          "class_name": "B3",
          "bbox_pixel": [
            242,
            325,
            472,
            569
          ]
        },
        {
          "side": "sisi_2",
          "side_index": 1,
          "box_index": 4,
          "class_name": "B3",
          "bbox_pixel": [
            702,
            290,
            888,
            495
          ]
        }
      ]
    },
    {
      "bunch_id": 3,
      "class": "B3",
      "class_mismatch": false,
      "appearance_count": 3,
      "appearances": [
        {
          "side": "sisi_1",
          "side_index": 0,
          "box_index": 2,
          "class_name": "B3",
          "bbox_pixel": [
            166,
            278,
            253,
            395
          ]
        },
        {
          "side": "sisi_2",
          "side_index": 1,
          "box_index": 1,
          "class_name": "B3",
          "bbox_pixel": [
            353,
            196,
            664,
            539
          ]
        },
        {
          "side": "sisi_3",
          "side_index": 2,
          "box_index": 6,
          "class_name": "B3",
          "bbox_pixel": [
            740,
            285,
            880,
            435
          ]
        }
      ]
    },
    {
      "bunch_id": 4,
      "class": "B4",
      "class_mismatch": false,
      "appearance_count": 2,
      "appearances": [
        {
          "side": "sisi_1",
          "side_index": 0,
          "box_index": 3,
          "class_name": "B4",
          "bbox_pixel": [
            265,
            160,
            392,
            319
          ]
        },
        {
          "side": "sisi_2",
          "side_index": 1,
          "box_index": 6,
          "class_name": "B4",
          "bbox_pixel": [
            642,
            87,
            730,
            181
          ]
        }
      ]
    },
    {
      "bunch_id": 5,
      "class": "B3",
      "class_mismatch": false,
      "appearance_count": 2,
      "appearances": [
        {
          "side": "sisi_1",
          "side_index": 0,
          "box_index": 4,
          "class_name": "B3",
          "bbox_pixel": [
            434,
            205,
            663,
            393
          ]
        },
        {
          "side": "sisi_2",
          "side_index": 1,
          "box_index": 5,
          "class_name": "B3",
          "bbox_pixel": [
            743,
            189,
            864,
            275
          ]
        }
      ]
    },
    {
      "bunch_id": 6,
      "class": "B3",
      "class_mismatch": false,
      "appearance_count": 2,
      "appearances": [
        {
          "side": "sisi_1",
          "side_index": 0,
          "box_index": 5,
          "class_name": "B3",
          "bbox_pixel": [
            726,
            273,
            920,
            428
          ]
        },
        {
          "side": "sisi_4",
          "side_index": 3,
          "box_index": 4,
          "class_name": "B3",
          "bbox_pixel": [
            58,
            315,
            304,
            660
          ]
        }
      ]
    },
    {
      "bunch_id": 7,
      "class": "B4",
      "class_mismatch": false,
      "appearance_count": 2,
      "appearances": [
        {
          "side": "sisi_1",
          "side_index": 0,
          "box_index": 6,
          "class_name": "B4",
          "bbox_pixel": [
            728,
            193,
            797,
            268
          ]
        },
        {
          "side": "sisi_4",
          "side_index": 3,
          "box_index": 3,
          "class_name": "B4",
          "bbox_pixel": [
            259,
            202,
            459,
            430
          ]
        }
      ]
    },
    {
      "bunch_id": 8,
      "class": "B2",
      "class_mismatch": false,
      "appearance_count": 1,
      "appearances": [
        {
          "side": "sisi_1",
          "side_index": 0,
          "box_index": 7,
          "class_name": "B2",
          "bbox_pixel": [
            547,
            411,
            779,
            609
          ]
        }
      ]
    },
    {
      "bunch_id": 9,
      "class": "B4",
      "class_mismatch": false,
      "appearance_count": 2,
      "appearances": [
        {
          "side": "sisi_2",
          "side_index": 1,
          "box_index": 2,
          "class_name": "B4",
          "bbox_pixel": [
            109,
            116,
            333,
            352
          ]
        },
        {
          "side": "sisi_3",
          "side_index": 2,
          "box_index": 5,
          "class_name": "B4",
          "bbox_pixel": [
            581,
            185,
            748,
            389
          ]
        }
      ]
    },
    {
      "bunch_id": 10,
      "class": "B3",
      "class_mismatch": false,
      "appearance_count": 3,
      "appearances": [
        {
          "side": "sisi_2",
          "side_index": 1,
          "box_index": 3,
          "class_name": "B3",
          "bbox_pixel": [
            123,
            339,
            349,
            597
          ]
        },
        {
          "side": "sisi_3",
          "side_index": 2,
          "box_index": 3,
          "class_name": "B3",
          "bbox_pixel": [
            298,
            330,
            635,
            590
          ]
        },
        {
          "side": "sisi_4",
          "side_index": 3,
          "box_index": 1,
          "class_name": "B3",
          "bbox_pixel": [
            707,
            325,
            909,
            498
          ]
        }
      ]
    },
    {
      "bunch_id": 11,
      "class": "B2",
      "class_mismatch": false,
      "appearance_count": 2,
      "appearances": [
        {
          "side": "sisi_3",
          "side_index": 2,
          "box_index": 0,
          "class_name": "B2",
          "bbox_pixel": [
            63,
            470,
            244,
            656
          ]
        },
        {
          "side": "sisi_4",
          "side_index": 3,
          "box_index": 0,
          "class_name": "B2",
          "bbox_pixel": [
            632,
            481,
            923,
            762
          ]
        }
      ]
    },
    {
      "bunch_id": 12,
      "class": "B4",
      "class_mismatch": false,
      "appearance_count": 1,
      "appearances": [
        {
          "side": "sisi_3",
          "side_index": 2,
          "box_index": 1,
          "class_name": "B4",
          "bbox_pixel": [
            326,
            165,
            492,
            297
          ]
        }
      ]
    },
    {
      "bunch_id": 13,
      "class": "B3",
      "class_mismatch": false,
      "appearance_count": 2,
      "appearances": [
        {
          "side": "sisi_3",
          "side_index": 2,
          "box_index": 2,
          "class_name": "B3",
          "bbox_pixel": [
            130,
            259,
            306,
            477
          ]
        },
        {
          "side": "sisi_4",
          "side_index": 3,
          "box_index": 2,
          "class_name": "B3",
          "bbox_pixel": [
            522,
            215,
            756,
            474
          ]
        }
      ]
    },
    {
      "bunch_id": 14,
      "class": "B3",
      "class_mismatch": false,
      "appearance_count": 1,
      "appearances": [
        {
          "side": "sisi_4",
          "side_index": 3,
          "box_index": 5,
          "class_name": "B3",
          "bbox_pixel": [
            367,
            414,
            586,
            662
          ]
        }
      ]
    }
  ],
  "_confirmedLinks": [
    {
      "linkId": "lnk-0",
      "sideA": 0,
      "bboxIdA": "b0",
      "sideB": 1,
      "bboxIdB": "b0"
    },
    {
      "linkId": "lnk-1",
      "sideA": 0,
      "bboxIdA": "b2",
      "sideB": 1,
      "bboxIdB": "b1"
    },
    {
      "linkId": "lnk-2",
      "sideA": 0,
      "bboxIdA": "b4",
      "sideB": 1,
      "bboxIdB": "b5"
    },
    {
      "linkId": "lnk-3",
      "sideA": 0,
      "bboxIdA": "b3",
      "sideB": 1,
      "bboxIdB": "b6"
    },
    {
      "linkId": "lnk-4",
      "sideA": 0,
      "bboxIdA": "b1",
      "sideB": 1,
      "bboxIdB": "b4"
    },
    {
      "linkId": "lnk-5",
      "sideA": 1,
      "bboxIdA": "b1",
      "sideB": 2,
      "bboxIdB": "b6"
    },
    {
      "linkId": "lnk-6",
      "sideA": 1,
      "bboxIdA": "b3",
      "sideB": 2,
      "bboxIdB": "b3"
    },
    {
      "linkId": "lnk-7",
      "sideA": 1,
      "bboxIdA": "b2",
      "sideB": 2,
      "bboxIdB": "b5"
    },
    {
      "linkId": "lnk-8",
      "sideA": 1,
      "bboxIdA": "b0",
      "sideB": 2,
      "bboxIdB": "b4"
    },
    {
      "linkId": "lnk-9",
      "sideA": 2,
      "bboxIdA": "b0",
      "sideB": 3,
      "bboxIdB": "b0"
    },
    {
      "linkId": "lnk-10",
      "sideA": 2,
      "bboxIdA": "b2",
      "sideB": 3,
      "bboxIdB": "b2"
    },
    {
      "linkId": "lnk-11",
      "sideA": 2,
      "bboxIdA": "b3",
      "sideB": 3,
      "bboxIdB": "b1"
    },
    {
      "linkId": "lnk-12",
      "sideA": 3,
      "bboxIdA": "b4",
      "sideB": 0,
      "bboxIdB": "b5"
    },
    {
      "linkId": "lnk-13",
      "sideA": 3,
      "bboxIdA": "b3",
      "sideB": 0,
      "bboxIdB": "b6"
    }
  ],
  "summary": {
    "total_unique_bunches": 14,
    "total_detections": 28,
    "duplicates_linked": 14,
    "by_class": {
      "B1": 1,
      "B2": 2,
      "B3": 7,
      "B4": 4,
      "other": 0
    },
    "by_side": {
      "sisi_1": 8,
      "sisi_2": 7,
      "sisi_3": 7,
      "sisi_4": 6
    }
  }
}