{
  "version": 1,
  "tree_id": "20260422-DAMIMAS-064",
  "tree_name": "DAMIMAS_A21B_0640",
  "split": "train",
  "metadata": {
    "date": "2026-04-22",
    "varietas": "DAMIMAS",
    "number": 64,
    "generated_at": "2026-04-22T04:21:25.100Z"
  },
  "images": {
    "sisi_1": {
      "filename": "DAMIMAS_A21B_0640_1.jpg",
      "label_file": "DAMIMAS_A21B_0640_1.txt",
      "side_index": 0,
      "side_label": "Sisi 1",
      "width": 960,
      "height": 1280,
      "bbox_count": 6,
      "annotations": [
        {
          "box_index": 0,
          "class_id": 1,
          "class_name": "B2",
          "bbox_yolo": [
            0.54936,
            0.321436,
            0.194036,
            0.208844
          ],
          "bbox_pixel": [
            434,
            278,
            621,
            545
          ]
        },
        {
          "box_index": 1,
          "class_id": 2,
          "class_name": "B3",
          "bbox_yolo": [
            0.288943,
            0.296926,
            0.216503,
            0.152676
          ],
          "bbox_pixel": [
            173,
            282,
            381,
            478
          ]
        },
        {
          "box_index": 2,
          "class_id": 3,
          "class_name": "B4",
          "bbox_yolo": [
            0.295752,
            0.202461,
            0.132081,
            0.063828
          ],
          "bbox_pixel": [
            221,
            218,
            347,
            300
          ]
        },
        {
          "box_index": 3,
          "class_id": 3,
          "class_name": "B4",
          "bbox_yolo": [
            0.496936,
            0.189696,
            0.132761,
            0.080167
          ],
          "bbox_pixel": [
            413,
            192,
            541,
            294
          ]
        },
        {
          "box_index": 4,
          "class_id": 2,
          "class_name": "B3",
          "bbox_yolo": [
            0.692674,
            0.258885,
            0.160675,
            0.162377
          ],
          "bbox_pixel": [
            588,
            227,
            742,
            435
          ]
        },
        {
          "box_index": 5,
          "class_id": 2,
          "class_name": "B3",
          "bbox_yolo": [
            0.780842,
            0.346712,
            0.11506,
            0.117443
          ],
          "bbox_pixel": [
            694,
            369,
            805,
            519
          ]
        }
      ]
    },
    "sisi_2": {
      "filename": "DAMIMAS_A21B_0640_2.jpg",
      "label_file": "DAMIMAS_A21B_0640_2.txt",
      "side_index": 1,
      "side_label": "Sisi 2",
      "width": 960,
      "height": 1280,
      "bbox_count": 6,
      "annotations": [
        {
          "box_index": 0,
          "class_id": 1,
          "class_name": "B2",
          "bbox_yolo": [
            0.215762,
            0.423222,
            0.232558,
            0.174989
          ],
          "bbox_pixel": [
            96,
            430,
            319,
            654
          ]
        },
        {
          "box_index": 1,
          "class_id": 2,
          "class_name": "B3",
          "bbox_yolo": [
            0.399681,
            0.338862,
            0.176319,
            0.162449
          ],
          "bbox_pixel": [
            299,
            330,
            468,
            538
          ]
        },
        {
          "box_index": 2,
          "class_id": 2,
          "class_name": "B3",
          "bbox_yolo": [
            0.192582,
            0.317202,
            0.113239,
            0.04617
          ],
          "bbox_pixel": [
            131,
            376,
            239,
            436
          ]
        },
        {
          "box_index": 3,
          "class_id": 2,
          "class_name": "B3",
          "bbox_yolo": [
            0.683539,
            0.362517,
            0.199878,
            0.160739
          ],
          "bbox_pixel": [
            560,
            361,
            752,
            567
          ]
        },
        {
          "box_index": 4,
          "class_id": 3,
          "class_name": "B4",
          "bbox_yolo": [
            0.584739,
            0.253648,
            0.167959,
            0.068399
          ],
          "bbox_pixel": [
            481,
            281,
            642,
            368
          ]
        },
        {
          "box_index": 5,
          "class_id": 1,
          "class_name": "B2",
          "bbox_yolo": [
            0.813497,
            0.408117,
            0.136039,
            0.180119
          ],
          "bbox_pixel": [
            716,
            407,
            846,
            638
          ]
        }
      ]
    },
    "sisi_3": {
      "filename": "DAMIMAS_A21B_0640_3.jpg",
      "label_file": "DAMIMAS_A21B_0640_3.txt",
      "side_index": 2,
      "side_label": "Sisi 3",
      "width": 960,
      "height": 1280,
      "bbox_count": 7,
      "annotations": [
        {
          "box_index": 0,
          "class_id": 0,
          "class_name": "B1",
          "bbox_yolo": [
            0.293866,
            0.47417,
            0.253058,
            0.165284
          ],
          "bbox_pixel": [
            161,
            501,
            404,
            713
          ]
        },
        {
          "box_index": 1,
          "class_id": 2,
          "class_name": "B3",
          "bbox_yolo": [
            0.258673,
            0.368276,
            0.112284,
            0.061589
          ],
          "bbox_pixel": [
            194,
            432,
            302,
            511
          ]
        },
        {
          "box_index": 2,
          "class_id": 2,
          "class_name": "B3",
          "bbox_yolo": [
            0.450561,
            0.421066,
            0.202782,
            0.128205
          ],
          "bbox_pixel": [
            335,
            457,
            530,
            621
          ]
        },
        {
          "box_index": 3,
          "class_id": 3,
          "class_name": "B4",
          "bbox_yolo": [
            0.415368,
            0.317371,
            0.124015,
            0.067873
          ],
          "bbox_pixel": [
            339,
            363,
            458,
            450
          ]
        },
        {
          "box_index": 4,
          "class_id": 2,
          "class_name": "B3",
          "bbox_yolo": [
            0.590891,
            0.338031,
            0.180419,
            0.095997
          ],
          "bbox_pixel": [
            481,
            371,
            654,
            494
          ]
        },
        {
          "box_index": 5,
          "class_id": 1,
          "class_name": "B2",
          "bbox_yolo": [
            0.722971,
            0.451134,
            0.158633,
            0.146548
          ],
          "bbox_pixel": [
            618,
            484,
            770,
            671
          ]
        },
        {
          "box_index": 6,
          "class_id": 2,
          "class_name": "B3",
          "bbox_yolo": [
            0.78799,
            0.364839,
            0.089869,
            0.067913
          ],
          "bbox_pixel": [
            713,
            424,
            800,
            510
          ]
        }
      ]
    },
    "sisi_4": {
      "filename": "DAMIMAS_A21B_0640_4.jpg",
      "label_file": "DAMIMAS_A21B_0640_4.txt",
      "side_index": 3,
      "side_label": "Sisi 4",
      "width": 960,
      "height": 1280,
      "bbox_count": 6,
      "annotations": [
        {
          "box_index": 0,
          "class_id": 0,
          "class_name": "B1",
          "bbox_yolo": [
            0.662561,
            0.405354,
            0.229596,
            0.223731
          ],
          "bbox_pixel": [
            526,
            376,
            746,
            662
          ]
        },
        {
          "box_index": 1,
          "class_id": 2,
          "class_name": "B3",
          "bbox_yolo": [
            0.3454,
            0.374246,
            0.265628,
            0.187908
          ],
          "bbox_pixel": [
            204,
            359,
            459,
            599
          ]
        },
        {
          "box_index": 2,
          "class_id": 1,
          "class_name": "B2",
          "bbox_yolo": [
            0.163566,
            0.346908,
            0.119826,
            0.169683
          ],
          "bbox_pixel": [
            100,
            335,
            215,
            553
          ]
        },
        {
          "box_index": 3,
          "class_id": 2,
          "class_name": "B3",
          "bbox_yolo": [
            0.301827,
            0.237242,
            0.190213,
            0.094897
          ],
          "bbox_pixel": [
            198,
            243,
            381,
            364
          ]
        },
        {
          "box_index": 4,
          "class_id": 2,
          "class_name": "B3",
          "bbox_yolo": [
            0.536869,
            0.268979,
            0.214513,
            0.153343
          ],
          "bbox_pixel": [
            412,
            246,
            618,
            442
          ]
        },
        {
          "box_index": 5,
          "class_id": 2,
          "class_name": "B3",
          "bbox_yolo": [
            0.778616,
            0.303544,
            0.087984,
            0.065359
          ],
          "bbox_pixel": [
            705,
            347,
            790,
            430
          ]
        }
      ]
    }
  },
  "bunches": [
    {
      "bunch_id": 1,
      "class": "B2",
      "class_mismatch": false,
      "appearance_count": 2,
      "appearances": [
        {
          "side": "sisi_1",
          "side_index": 0,
          "box_index": 0,
          "class_name": "B2",
          "bbox_pixel": [
            434,
            278,
            621,
            545
          ]
        },
        {
          "side": "sisi_2",
          "side_index": 1,
          "box_index": 5,
          "class_name": "B2",
          "bbox_pixel": [
            716,
            407,
            846,
            638
          ]
        }
      ]
    },
    {
      "bunch_id": 2,
      "class": "B3",
      "class_mismatch": false,
      "appearance_count": 2,
      "appearances": [
        {
          "side": "sisi_1",
          "side_index": 0,
          "box_index": 1,
          "class_name": "B3",
          "bbox_pixel": [
            173,
            282,
            381,
            478
          ]
        },
        {
          "side": "sisi_2",
          "side_index": 1,
          "box_index": 3,
          "class_name": "B3",
          "bbox_pixel": [
            560,
            361,
            752,
            567
          ]
        }
      ]
    },
    {
      "bunch_id": 3,
      "class": "B4",
      "class_mismatch": false,
      "appearance_count": 2,
      "appearances": [
        {
          "side": "sisi_1",
          "side_index": 0,
          "box_index": 2,
          "class_name": "B4",
          "bbox_pixel": [
            221,
            218,
            347,
            300
          ]
        },
        {
          "side": "sisi_2",
          "side_index": 1,
          "box_index": 4,
          "class_name": "B4",
          "bbox_pixel": [
            481,
            281,
            642,
            368
          ]
        }
      ]
    },
    {
      "bunch_id": 4,
      "class": "B4",
      "class_mismatch": false,
      "appearance_count": 1,
      "appearances": [
        {
          "side": "sisi_1",
          "side_index": 0,
          "box_index": 3,
          "class_name": "B4",
          "bbox_pixel": [
            413,
            192,
            541,
            294
          ]
        }
      ]
    },
    {
      "bunch_id": 5,
      "class": "B3",
      "class_mismatch": false,
      "appearance_count": 2,
      "appearances": [
        {
          "side": "sisi_1",
          "side_index": 0,
          "box_index": 4,
          "class_name": "B3",
          "bbox_pixel": [
            588,
            227,
            742,
            435
          ]
        },
        {
          "side": "sisi_4",
          "side_index": 3,
          "box_index": 3,
          "class_name": "B3",
          "bbox_pixel": [
            198,
            243,
            381,
            364
          ]
        }
      ]
    },
    {
      "bunch_id": 6,
      "class": "B3",
      "class_mismatch": false,
      "appearance_count": 2,
      "appearances": [
        {
          "side": "sisi_1",
          "side_index": 0,
          "box_index": 5,
          "class_name": "B3",
          "bbox_pixel": [
            694,
            369,
            805,
            519
          ]
        },
        {
          "side": "sisi_4",
          "side_index": 3,
          "box_index": 1,
          "class_name": "B3",
          "bbox_pixel": [
            204,
            359,
            459,
            599
          ]
        }
      ]
    },
    {
      "bunch_id": 7,
      "class": "B2",
      "class_mismatch": false,
      "appearance_count": 2,
      "appearances": [
        {
          "side": "sisi_2",
          "side_index": 1,
          "box_index": 0,
          "class_name": "B2",
          "bbox_pixel": [
            96,
            430,
            319,
            654
          ]
        },
        {
          "side": "sisi_3",
          "side_index": 2,
          "box_index": 5,
          "class_name": "B2",
          "bbox_pixel": [
            618,
            484,
            770,
            671
          ]
        }
      ]
    },
    {
      "bunch_id": 8,
      "class": "B3",
      "class_mismatch": false,
      "appearance_count": 2,
      "appearances": [
        {
          "side": "sisi_2",
          "side_index": 1,
          "box_index": 1,
          "class_name": "B3",
          "bbox_pixel": [
            299,
            330,
            468,
            538
          ]
        },
        {
          "side": "sisi_3",
          "side_index": 2,
          "box_index": 6,
          "class_name": "B3",
          "bbox_pixel": [
            713,
            424,
            800,
            510
          ]
        }
      ]
    },
    {
      "bunch_id": 9,
      "class": "B3",
      "class_mismatch": false,
      "appearance_count": 2,
      "appearances": [
        {
          "side": "sisi_2",
          "side_index": 1,
          "box_index": 2,
          "class_name": "B3",
          "bbox_pixel": [
            131,
            376,
            239,
            436
          ]
        },
        {
          "side": "sisi_3",
          "side_index": 2,
          "box_index": 4,
          "class_name": "B3",
          "bbox_pixel": [
            481,
            371,
            654,
            494
          ]
        }
      ]
    },
    {
      "bunch_id": 10,
      "class": "B1",
      "class_mismatch": false,
      "appearance_count": 2,
      "appearances": [
        {
          "side": "sisi_3",
          "side_index": 2,
          "box_index": 0,
          "class_name": "B1",
          "bbox_pixel": [
            161,
            501,
            404,
            713
          ]
        },
        {
          "side": "sisi_4",
          "side_index": 3,
          "box_index": 0,
          "class_name": "B1",
          "bbox_pixel": [
            526,
            376,
            746,
            662
          ]
        }
      ]
    },
    {
      "bunch_id": 11,
      "class": "B3",
      "class_mismatch": false,
      "appearance_count": 2,
      "appearances": [
        {
          "side": "sisi_3",
          "side_index": 2,
          "box_index": 1,
          "class_name": "B3",
          "bbox_pixel": [
            194,
            432,
            302,
            511
          ]
        },
        {
          "side": "sisi_4",
          "side_index": 3,
          "box_index": 4,
          "class_name": "B3",
          "bbox_pixel": [
            412,
            246,
            618,
            442
          ]
        }
      ]
    },
    {
      "bunch_id": 12,
      "class": "B3",
      "class_mismatch": false,
      "appearance_count": 2,
      "appearances": [
        {
          "side": "sisi_3",
          "side_index": 2,
          "box_index": 2,
          "class_name": "B3",
          "bbox_pixel": [
            335,
            457,
            530,
            621
          ]
        },
        {
          "side": "sisi_4",
          "side_index": 3,
          "box_index": 5,
          "class_name": "B3",
          "bbox_pixel": [
            705,
            347,
            790,
            430
          ]
        }
      ]
    },
    {
      "bunch_id": 13,
      "class": "B4",
      "class_mismatch": false,
      "appearance_count": 1,
      "appearances": [
        {
          "side": "sisi_3",
          "side_index": 2,
          "box_index": 3,
          "class_name": "B4",
          "bbox_pixel": [
            339,
            363,
            458,
            450
          ]
        }
      ]
    },
    {
      "bunch_id": 14,
      "class": "B2",
      "class_mismatch": false,
      "appearance_count": 1,
      "appearances": [
        {
          "side": "sisi_4",
          "side_index": 3,
          "box_index": 2,
          "class_name": "B2",
          "bbox_pixel": [
            100,
            335,
            215,
            553
          ]
        }
      ]
    }
  ],
  "_confirmedLinks": [
    {
      "linkId": "lnk-2",
      "sideA": 0,
      "bboxIdA": "b2",
      "sideB": 1,
      "bboxIdB": "b4"
    },
    {
      "linkId": "lnk-3",
      "sideA": 0,
      "bboxIdA": "b0",
      "sideB": 1,
      "bboxIdB": "b5"
    },
    {
      "linkId": "lnk-4",
      "sideA": 0,
      "bboxIdA": "b1",
      "sideB": 1,
      "bboxIdB": "b3"
    },
    {
      "linkId": "lnk-5",
      "sideA": 1,
      "bboxIdA": "b1",
      "sideB": 2,
      "bboxIdB": "b6"
    },
    {
      "linkId": "lnk-6",
      "sideA": 1,
      "bboxIdA": "b0",
      "sideB": 2,
      "bboxIdB": "b5"
    },
    {
      "linkId": "lnk-7",
      "sideA": 1,
      "bboxIdA": "b2",
      "sideB": 2,
      "bboxIdB": "b4"
    },
    {
      "linkId": "lnk-8",
      "sideA": 2,
      "bboxIdA": "b0",
      "sideB": 3,
      "bboxIdB": "b0"
    },
    {
      "linkId": "lnk-9",
      "sideA": 2,
      "bboxIdA": "b1",
      "sideB": 3,
      "bboxIdB": "b4"
    },
    {
      "linkId": "lnk-10",
      "sideA": 2,
      "bboxIdA": "b2",
      "sideB": 3,
      "bboxIdB": "b5"
    },
    {
      "linkId": "lnk-11",
      "sideA": 3,
      "bboxIdA": "b1",
      "sideB": 0,
      "bboxIdB": "b5"
    },
    {
      "linkId": "lnk-12",
      "sideA": 3,
      "bboxIdA": "b3",
      "sideB": 0,
      "bboxIdB": "b4"
    }
  ],
  "summary": {
    "total_unique_bunches": 14,
    "total_detections": 25,
    "duplicates_linked": 11,
    "by_class": {
      "B1": 1,
      "B2": 3,
      "B3": 7,
      "B4": 3,
      "other": 0
    },
    "by_side": {
      "sisi_1": 6,
      "sisi_2": 6,
      "sisi_3": 7,
      "sisi_4": 6
    }
  }
}